LICENSE
MANIFEST.in
README.rst
hexgrid.py
setup.py
test.py
hexgrid_py.egg-info/PKG-INFO
hexgrid_py.egg-info/SOURCES.txt
hexgrid_py.egg-info/dependency_links.txt
hexgrid_py.egg-info/requires.txt
hexgrid_py.egg-info/top_level.txt