Metadata-Version: 1.1
Name: hexgrid-py
Version: 1.1
Summary: HexGrid
Home-page: https://github.com/gojuno/hexgrid-py
Author: Alexander Verbitsky
Author-email: averbitsky@gojuno.com
License: BSD
Keywords: hexgrid
Platform: UNKNOWN
Classifier: Development Status :: 5 - Production/Stable
Classifier: Topic :: Utilities
Classifier: Programming Language :: Python
Classifier: License :: OSI Approved :: BSD License
